LICENSE
MANIFEST.in
README.rst
setup.py
gcm_clerk/__init__.py
gcm_clerk/gcm.py
gcm_clerk/test.py
gcm_clerk.egg-info/PKG-INFO
gcm_clerk.egg-info/SOURCES.txt
gcm_clerk.egg-info/dependency_links.txt
gcm_clerk.egg-info/requires.txt
gcm_clerk.egg-info/top_level.txt