Metadata-Version: 1.1
Name: gcm-clerk
Version: 0.1.4
Summary: Python client for Google Cloud Messaging (GCM)
Home-page: https://bitbucket.org/aleksihoffman/gcm-clerk
Author: Aleksi Hoffman
Author-email: aleksi@lekksi.com
License: Apache 2.0
Keywords: gcm push notification google cloud messaging android
Platform: UNKNOWN
Classifier: Development Status :: 4 - Beta
Classifier: Intended Audience :: Developers
Classifier: License :: OSI Approved :: Apache Software License
Classifier: Programming Language :: Python
Classifier: Topic :: Software Development :: Libraries :: Python Modules
